Metadata-Version: 2.1
Name: taxomatcher
Version: 0.2
Summary: A tool for parsing and extracting taxon synonyms.
Home-page: https://github.com/Lswhiteh/taxomatcher
Author: Logan Whitehouse
Author-email: lswhiteh@unc.edu
License: MIT
Project-URL: Issues, https://github.com/Lswhiteh/taxomatcher/issues
Project-URL: GitHub, https://github.com/Lswhiteh/taxomatcher
Keywords: population genetics,phylogenetics,taxonomy
Classifier: Programming Language :: Python :: 3
Classifier: Operating System :: OS Independent
Requires-Python: >=3.6
License-File: LICENSE
